README.md
setup.py
ufs_sdk/__init__.py
ufs_sdk/api.py
ufs_sdk/exceptions.py
ufs_sdk/request.py
ufs_sdk/session.py
ufs_sdk/utils.py
ufs_sdk.egg-info/PKG-INFO
ufs_sdk.egg-info/SOURCES.txt
ufs_sdk.egg-info/dependency_links.txt
ufs_sdk.egg-info/requires.txt
ufs_sdk.egg-info/top_level.txt
ufs_sdk/wrapper/__init__.py
ufs_sdk/wrapper/requests.py
ufs_sdk/wrapper/types.py