Metadata-Version: 1.1
Name: ufs-sdk
Version: 1.3.1
Summary: UFS Python SDK
Home-page: https://github.com/tmconsulting/ufs-python-sdk
Author: Travel Managment Consulting
Author-email: otd@tm-consulting.ru
License: MIT License
Download-URL: https://github.com/tmconsulting/ufs-python-sdk/archive/1.3.1.tar.gz
Platform: UNKNOWN
Classifier: Environment :: Web Environment
Classifier: Intended Audience :: Developers
Classifier: License :: OSI Approved :: MIT License
Classifier: Programming Language :: Python :: 3.6
Classifier: Topic :: Software Development :: Libraries :: Python Modules
